logginginitializer/__init__.py
logginginitializer/logging_config.py
logginginitializer/logging_initializer.py
logginginitializer/py.typed
logginginitializer-1.2.0.dist-info/LICENSE
logginginitializer-1.2.0.dist-info/METADATA
logginginitializer-1.2.0.dist-info/WHEEL
logginginitializer-1.2.0.dist-info/top_level.txt
logginginitializer-1.2.0.dist-info/RECORD
