Metadata-Version: 2.1
Name: logginginitializer
Version: 1.2.0
Summary: Initialize Python logging with RWS Datalab defaults
Author-email: RWS Datalab <datalab.codebase@rws.nl>
Project-URL: homepage, https://gitlab.com/rwsdatalab/codebase/utils/logging-initializer
Project-URL: documentation, https://rwsdatalab.gitlab.io/codebase/utils/logging-initializer
Project-URL: repository, https://gitlab.com/rwsdatalab/codebase/utils/logging-initializer
Project-URL: changelog, https://gitlab.com/rwsdatalab/codebase/utils/logging-initializer/blob/main/CHANGELOG.rst
Keywords: logginginitializer
Classifier: Development Status :: 5 - Production/Stable
Classifier: Intended Audience :: Developers
Classifier: Natural Language :: English
Classifier: Programming Language :: Python :: 3
Classifier: Programming Language :: Python :: 3.7
Classifier: Programming Language :: Python :: 3.8
Classifier: Programming Language :: Python :: 3.9
Classifier: Programming Language :: Python :: 3.10
Classifier: Programming Language :: Python :: 3.11
Requires-Python: >=3.10
License-File: LICENSE
Requires-Dist: pydantic >=2
Provides-Extra: dev
Requires-Dist: bandit ; extra == 'dev'
Requires-Dist: black ; extra == 'dev'
Requires-Dist: flake8 ; extra == 'dev'
Requires-Dist: flake8-bugbear ; extra == 'dev'
Requires-Dist: flake8-comprehensions ; extra == 'dev'
Requires-Dist: flake8-docstrings ; extra == 'dev'
Requires-Dist: flake8-polyfill ; extra == 'dev'
Requires-Dist: isort ; extra == 'dev'
Requires-Dist: mypy ; extra == 'dev'
Requires-Dist: pre-commit ; extra == 'dev'
Requires-Dist: pylint ; extra == 'dev'
Requires-Dist: pytest ; extra == 'dev'
Requires-Dist: pytest-cov ; extra == 'dev'
Requires-Dist: radon ; extra == 'dev'
Requires-Dist: safety ; extra == 'dev'
Provides-Extra: doc
Requires-Dist: pydata-sphinx-theme ; extra == 'doc'
Requires-Dist: sphinx ; extra == 'doc'
Requires-Dist: sphinx-autodoc-typehints ; extra == 'doc'
